uci_test_suite/__init__.py
uci_test_suite/__main__.py
uci_test_suite/engine.py
uci_test_suite/tests.py
uci_test_suite-0.1.1.dist-info/licenses/LICENSE
uci_test_suite-0.1.1.dist-info/METADATA
uci_test_suite-0.1.1.dist-info/WHEEL
uci_test_suite-0.1.1.dist-info/entry_points.txt
uci_test_suite-0.1.1.dist-info/top_level.txt
uci_test_suite-0.1.1.dist-info/RECORD
