Metadata-Version: 2.4
Name: uci-test-suite
Version: 0.1.1
Summary: A Python-based set of tests for UCI server/chess engine implementations
Author-email: Alex Myodov <amyodov@gmail.com>
License: MIT License
Keywords: chess,UCI,chess engine,testing,test suite,uci protocol,uci chess
Classifier: Development Status :: 3 - Alpha
Classifier: Intended Audience :: Developers
Classifier: Topic :: Games/Entertainment :: Board Games
Classifier: Topic :: Software Development :: Testing
Classifier: License :: OSI Approved :: MIT License
Classifier: Programming Language :: Python :: 3
Classifier: Programming Language :: Python :: 3.10
Classifier: Programming Language :: Python :: 3.11
Classifier: Programming Language :: Python :: 3.12
Classifier: Programming Language :: Python :: 3.13
Classifier: Operating System :: OS Independent
Requires-Python: >=3.10
License-File: LICENSE
Requires-Dist: chess<2.0.0,>=1.11.2
Requires-Dist: click<9.0.0,>=8.1.8
Provides-Extra: dev
Requires-Dist: pytest>=8.3.0; extra == "dev"
Requires-Dist: ruff>=0.11.4; extra == "dev"
Requires-Dist: uv-publish>=1.2; extra == "dev"
Dynamic: license-file
